{
  "@context": "https://schema.org",
  "@graph": [
    {
      "@type": "SoftwareApplication",
      "name": "JPG en PDF",
      "description": "Convertissez et assemblez vos photos JPG ou PNG en un seul fichier PDF de haute qualité. Facile et sécurisé.",
      "applicationCategory": "UtilitiesApplication",
      "operatingSystem": "All",
      "offers": {
        "@type": "Offer",
        "price": "0",
        "priceCurrency": "EUR"
      },
      "browserRequirements": "Requires JavaScript. Works in Chrome, Firefox, Safari, Edge."
    },
    {
      "@type": "FAQPage",
      "mainEntity": [
        {
          "@type": "Question",
          "name": "Comment convertir une ou plusieurs images JPG en un PDF ?",
          "acceptedAnswer": {
            "@type": "Answer",
            "text": "Déposez vos images JPG dans la zone de dépôt, organisez-les selon l'ordre souhaité et cliquez sur \"Convertir en PDF\" pour les fusionner."
          }
        },
        {
          "@type": "Question",
          "name": "Les images sont-elles compressées lors de la conversion ?",
          "acceptedAnswer": {
            "@type": "Answer",
            "text": "Vous pouvez ajuster les marges et l'orientation pour optimiser la mise en page sans dégrader la résolution de vos photos."
          }
        },
        {
          "@type": "Question",
          "name": "Quels formats d'images sont pris en charge ?",
          "acceptedAnswer": {
            "@type": "Answer",
            "text": "L'outil accepte les formats JPG, JPEG, PNG, WebP et GIF pour créer votre document PDF final."
          }
        }
      ]
    },
    {
      "@type": "BreadcrumbList",
      "itemListElement": [
        {
          "@type": "ListItem",
          "position": 1,
          "name": "Accueil",
          "item": "https://ilovedoc-ten.vercel.app"
        },
        {
          "@type": "ListItem",
          "position": 2,
          "name": "JPG en PDF",
          "item": "https://ilovedoc-ten.vercel.app/jpg-to-pdf"
        }
      ]
    },
    {
      "@type": "HowTo",
      "name": "Comment utiliser JPG en PDF en ligne",
      "description": "Convertissez et assemblez vos photos JPG ou PNG en un seul fichier PDF de haute qualité. Facile et sécurisé.",
      "step": [
        {
          "@type": "HowToStep",
          "position": 1,
          "name": "Déposer les images",
          "text": "Importez vos fichiers JPG ou PNG dans la zone de téléchargement.",
          "url": "https://ilovedoc-ten.vercel.app/jpg-to-pdf#step-1"
        },
        {
          "@type": "HowToStep",
          "position": 2,
          "name": "Ajuster les options",
          "text": "Définissez l'orientation des pages, la taille des marges et l'ordre des images.",
          "url": "https://ilovedoc-ten.vercel.app/jpg-to-pdf#step-2"
        },
        {
          "@type": "HowToStep",
          "position": 3,
          "name": "Compiler le PDF",
          "text": "Cliquez sur le bouton pour générer le document PDF localement.",
          "url": "https://ilovedoc-ten.vercel.app/jpg-to-pdf#step-3"
        },
        {
          "@type": "HowToStep",
          "position": 4,
          "name": "Télécharger le fichier",
          "text": "Récupérez votre document PDF contenant toutes vos images.",
          "url": "https://ilovedoc-ten.vercel.app/jpg-to-pdf#step-4"
        }
      ]
    }
  ]
}